magoplotlib/__init__.py
magoplotlib/add.py
magoplotlib-0.0.2.dist-info/LICENSE
magoplotlib-0.0.2.dist-info/METADATA
magoplotlib-0.0.2.dist-info/WHEEL
magoplotlib-0.0.2.dist-info/top_level.txt
magoplotlib-0.0.2.dist-info/RECORD
